drms/CITATION.rst
drms/__init__.py
drms/_version.py
drms/client.py
drms/config.py
drms/exceptions.py
drms/json.py
drms/main.py
drms/utils.py
drms/version.py
drms/tests/__init__.py
drms/tests/conftest.py
drms/tests/test_client.py
drms/tests/test_config.py
drms/tests/test_exceptions.py
drms/tests/test_init.py
drms/tests/test_jsoc_basic.py
drms/tests/test_jsoc_email.py
drms/tests/test_jsoc_export.py
drms/tests/test_jsoc_info.py
drms/tests/test_jsoc_query.py
drms/tests/test_json.py
drms/tests/test_kis_basic.py
drms/tests/test_main.py
drms/tests/test_series_info.py
drms/tests/test_to_datetime.py
drms/tests/test_utils.py
drms-0.8.0.dist-info/LICENSE.rst
drms-0.8.0.dist-info/METADATA
drms-0.8.0.dist-info/WHEEL
drms-0.8.0.dist-info/entry_points.txt
drms-0.8.0.dist-info/top_level.txt
drms-0.8.0.dist-info/RECORD
