Metadata-Version: 2.1
Name: drms
Version: 0.8.0
Summary: Access HMI, AIA and MDI data from the Standford JSOC DRMS
Home-page: https://sunpy.org
Author: The SunPy Community
Author-email: sunpy@googlegroups.com
License: BSD 2-Clause
Keywords: solar physics,solar,science,data
Platform: any
Classifier: Development Status :: 5 - Production/Stable
Classifier: Intended Audience :: Science/Research
Classifier: License :: OSI Approved :: BSD License
Classifier: Natural Language :: English
Classifier: Operating System :: OS Independent
Classifier: Programming Language :: Python
Classifier: Programming Language :: Python :: 3
Classifier: Programming Language :: Python :: 3.10
Classifier: Programming Language :: Python :: 3.11
Classifier: Programming Language :: Python :: 3.12
Classifier: Topic :: Scientific/Engineering :: Astronomy
Classifier: Topic :: Scientific/Engineering :: Physics
Provides: drms
Requires-Python: >=3.10
License-File: LICENSE.rst
Requires-Dist: numpy
Requires-Dist: pandas
Requires-Dist: packaging
Provides-Extra: all
Provides-Extra: dev
Requires-Dist: pytest-astropy ; extra == 'dev'
Requires-Dist: tox ; extra == 'dev'
Requires-Dist: astropy ; extra == 'dev'
Requires-Dist: matplotlib ; extra == 'dev'
Requires-Dist: sphinx ; extra == 'dev'
Requires-Dist: sphinx-automodapi ; extra == 'dev'
Requires-Dist: sphinx-changelog ; extra == 'dev'
Requires-Dist: sphinx-copybutton ; extra == 'dev'
Requires-Dist: sphinx-gallery ; extra == 'dev'
Requires-Dist: sphinx-hoverxref ; extra == 'dev'
Requires-Dist: sphinxext-opengraph ; extra == 'dev'
Requires-Dist: sunpy-sphinx-theme ; extra == 'dev'
Requires-Dist: importlib-resources <6 ; extra == 'dev'
Provides-Extra: docs
Requires-Dist: astropy ; extra == 'docs'
Requires-Dist: matplotlib ; extra == 'docs'
Requires-Dist: sphinx ; extra == 'docs'
Requires-Dist: sphinx-automodapi ; extra == 'docs'
Requires-Dist: sphinx-changelog ; extra == 'docs'
Requires-Dist: sphinx-copybutton ; extra == 'docs'
Requires-Dist: sphinx-gallery ; extra == 'docs'
Requires-Dist: sphinx-hoverxref ; extra == 'docs'
Requires-Dist: sphinxext-opengraph ; extra == 'docs'
Requires-Dist: sunpy-sphinx-theme ; extra == 'docs'
Requires-Dist: importlib-resources <6 ; extra == 'docs'
Provides-Extra: tests
Requires-Dist: pytest-astropy ; extra == 'tests'
Requires-Dist: tox ; extra == 'tests'
